{
  "internal_data": {
    "created_at": null,
    "updated_at": null,
    "updated_by": null
  },
  "external_data": {
    "company_number": "OE623672",
    "id": "ERyiOut_ZiY1GMAZbkeN6PLCDNc",
    "psc_id" : "AoRE4bhxdSdXur_NLdfh4JF81Y4",
    "notification_id": "ERyiOut_ZiY1GMAZbkeN6PLCDNc",
    "psc_statement_id" : "UKWLhOXMpdjzt-Maq7hbxAyPyQs",
    "data" : {
      "kind" : "individual-beneficial-owner",
      "is_sanctioned": true,
      "service_address" : {
        "premises": "3",
        "address_line_1": "Clos Rhiannon",
        "address_line_2": "Thornhill",
        "locality": "Cardiff",
        "country": "Wales",
        "postal_code": "CF14 9HQ",
        "region": "Here",
        "care_of": "CareOf",
        "po_box": "PoBox"
      },
      "principal_office_address": null,
      "natures_of_control": [
        "ownership-of-shares-more-than-25-percent-registered-overseas-entity",
        "voting-rights-more-than-25-percent-registered-overseas-entity",
        "right-to-appoint-and-remove-directors-registered-overseas-entity",
        "significant-influence-or-control-registered-overseas-entity"
      ],
      "links": [
        {
          "self": "/company/OE623672/persons-with-significant-control/individual-beneficial-owner/ERyiOut_ZiY1GMAZbkeN6PLCDNc",
          "statements": "/company/OE623672/persons-with-significant-control-statements/UKWLhOXMpdjzt-Maq7hbxAyPyQs"
        }
      ],
      "ceased_on": [2018, 2, 1],
      "notification_date": [2016, 1, 1],
      "notified_on": [2016, 1, 1],
      "company_number": null,
      "country_of_residence": "Italy",
      "description": null,
      "identification": {
        "country_registered": null,
        "legal_authority": null,
        "legal_form": null,
        "place_registered": null,
        "registration_number": null
      },
      "name": "Mr John Dave Smith",
      "name_elements": {
        "forename": "John",
        "surname": "Smith",
        "title": "Mr",
        "middle_name": "Dave"
      },
      "nationality": "Italian",
      "service_address_same_as_registered_office_address": true
    },
    "internal_id": "4",
    "sensitive_data": {
      "date_of_birth": {
        "day": 12,
        "month": 7,
        "year": 1994
      },
      "residential_address_same_as_service_address": true,
      "usual_residential_address": {
        "address_line_1": "Clos Rhiannon",
        "address_line_2": "Thornhill",
        "care_of": "CareOf",
        "country": "Wales",
        "locality": "Cardiff",
        "po_box": "PoBox",
        "postal_code": "CF14 9HQ",
        "premise": "3",
        "region": "Here"
      }
    }
  }
}